snipbackground/__init__.py
snipbackground/snip.py
snipbackground-0.1.5.dist-info/METADATA
snipbackground-0.1.5.dist-info/WHEEL
snipbackground-0.1.5.dist-info/top_level.txt
snipbackground-0.1.5.dist-info/RECORD
