Metadata-Version: 2.4
Name: snipbackground
Version: 0.1.5
Summary: Fast CPU-based SNIP background subtraction
Author: Yifan Yao
Requires-Python: >=3.8
